[{"text":"So here is just going to be a rotate. ","width":3264},{"text":"And because the sound is going to.","width":64},{"text":" Oh, no. ","width":256},{"text":"That case will never occur.","width":256},{"text":"so","width":64},{"text":"I wouldn't be any rebounce function if it is zero. ","width":448},{"text":"Equals zero I heard something","width":320},{"text":"Yeah","width":128},{"text":"OK","width":128},{"text":"So","width":64},{"text":"When we are figuring out,","width":192},{"text":"We are locking at the bounce function at that child.","width":256},{"text":"It couldn't be minus one or positive two.","width":256},{"text":"Because everything we are looking at a child ","width":384},{"text":"everything will not be zero","width":192},{"text":"So we look at either child or some node,","width":128},{"text":"we know the trees cannot have a bounce factor","width":256},{"text":"less than minus one of greater than one","width":512},{"text":"We look them from the bottom up, so everything below us are ","width":320},{"text":"so we don't actually have to worry about everything other than one or minus one.","width":256},{"text":"It won't even be zero because it is inbalanced, so","width":320},{"text":"So we know it has to be one on, somewhere.","width":320},{"text":"So","width":256},{"text":"the balance factors agree","width":192},{"text":"we just do a simple rivertation","width":192},{"text":"in these other cases the balance indicators don't agree","width":320},{"text":"we have to do double rotation","width":64},{"text":"which double rotation is it going to be","width":128},{"text":"it can be a left-right","width":256},{"text":"this is a right rotation","width":576},{"text":" we are going to do a ","width":320},{"text":"right rotation","width":512},{"text":"is it make sense","width":832},{"text":"yes","width":64},{"text":"this case","width":128},{"text":"like","width":512},{"text":"the balance factor is still two","width":1664},{"text":"now look at the balance factor at this guy","width":896},{"text":" the left side is minus one","width":320},{"text":"one minus one is minus two","width":1088},{"text":"so ","width":128},{"text":"ok","width":512},{"text":"this id fine","width":128},{"text":"there we go","width":640},{"text":"sorry","width":256},{"text":" this sub tree has height 2","width":640},{"text":"so the balance factor of this tree is 2","width":512},{"text":"this tree","width":192},{"text":"balance factor is 2","width":448},{"text":"this is the right picture","width":256},{"text":"the root tree has 2","width":512},{"text":"because it is 2 on the left","width":512},{"text":"this left tree is an AVL tree","width":448},{"text":"so the balance factor is ","width":64},{"text":"the only case is if it is one","width":512},{"text":"which is heavy on the left","width":320},{"text":"so ","width":64},{"text":"like this ","width":640},{"text":"where ","width":128},{"text":"this balance factor is 1","width":384},{"text":" this is height 2","width":384},{"text":" this is height 0","width":128},{"text":"looks like a single rotation","width":448},{"text":"like a right node","width":256},{"text":"on the other case","width":256},{"text":"the root is heavy on its left","width":576},{"text":"but the child is heavy on the right","width":512},{"text":"angle in the tree","width":192},{"text":" so you first have to do a ","width":320},{"text":"left rotate ","width":384},{"text":"about the child node","width":192},{"text":"and then a right rotate","width":320}]