[{"text":"Okay ready?","width":832},{"text":"Ready?","width":128},{"text":"Alright","width":64},{"text":"So I'm executing this code and the first thing I do is ask for a new derived class thing.","width":448},{"text":"What is the first output that I see?","width":256},{"text":"Constructor of...?","width":64},{"text":"What order do constructors go in?","width":384},{"text":"Constructor of...?","width":192},{"text":"Base!","width":128},{"text":"Good. So the result of the first statement is constructor of base","width":384},{"text":"And then because its a derived class thing, the next thing I see is.....","width":576},{"text":"Constructor of dervied","width":192},{"text":"Now the interesting things begin","width":320},{"text":"I'm doing two colors of ink here and the reason for that is because","width":512},{"text":"I'm going to go with what you hope. What do you hope happens here?","width":192},{"text":"So what you hope is....somebody say..somebody volunteer","width":960},{"text":"What do you hope happens here?","width":128},{"text":"Ok so what you hope happens is...Dtor:D and Dtor:B","width":832},{"text":"Anybody strongly disagree with the hope here?","width":128},{"text":"That feels like it would be responsible right?","width":384},{"text":"Guess what really does happen","width":256},{"text":"Which one? Only one of them goes by default","width":448},{"text":"Raise your hand if you think its derived goes....","width":384},{"text":"Raise your hand if you think its base goes....","width":192},{"text":"Okay so 50/50","width":64},{"text":"So what I take from that is that collectively we're guessing","width":384},{"text":"What goes is Dtor:B","width":512},{"text":"The question is...how do we make Dtor:D go...","width":1280},{"text":"and the answer is the we make the base class destructor virtual","width":320},{"text":"and then the right thing will happen","width":704},{"text":"Thats what causes Dtor:D","width":384},{"text":"and thats it! That just how it works!","width":512},{"text":"If only Dtor:B was printed...think about what that means if there was dynamic memory associated with it.","width":768},{"text":"There would be a memory leak","width":64},{"text":"The question is...do we need the virtual keyword in front of the derived class destructor","width":1088},{"text":"I believe that implicitly its there but I'm not sure so yes you should put it there","width":256},{"text":"Anytime you are creating a class that might be a base class","width":320},{"text":"just make your destructors virtual","width":128}]